chembl_structure_pipeline/__init__.py
chembl_structure_pipeline/checker.py
chembl_structure_pipeline/exclude_flag.py
chembl_structure_pipeline/standardizer.py
chembl_structure_pipeline/data/salts.smi
chembl_structure_pipeline/data/solvents.smi
chembl_structure_pipeline-1.2.2.dist-info/LICENSE
chembl_structure_pipeline-1.2.2.dist-info/METADATA
chembl_structure_pipeline-1.2.2.dist-info/WHEEL
chembl_structure_pipeline-1.2.2.dist-info/top_level.txt
chembl_structure_pipeline-1.2.2.dist-info/RECORD
