Metadata-Version: 2.1
Name: chembl-structure-pipeline
Version: 1.2.2
Summary: ChEMBL Structure Pipeline
Home-page: https://www.ebi.ac.uk/chembl/
Author: Greg Landrum, Eloy Félix
Author-email: greg.landrum@t5informatics.com
License: MIT
License-File: LICENSE
Requires-Dist: setuptools >=46.4.0
Requires-Dist: rdkit >=2022.09.01
